[
  {
    "id": "homepage",
    "title": "Homepage",
    "lastUpdated": "2025-05-07T23:09:59.475Z",
    "author": "Content Writer Agent",
    "status": "pending"
  },
  {
    "id": "services-overview",
    "title": "Services Overview",
    "lastUpdated": "2025-05-07T23:10:35.615Z",
    "author": "Content Writer Agent",
    "status": "pending"
  },
  {
    "id": "about",
    "title": "About",
    "lastUpdated": "2025-05-07T23:10:57.107Z",
    "author": "Content Writer Agent",
    "status": "pending"
  },
  {
    "id": "contact",
    "title": "Contact",
    "lastUpdated": "2025-05-07T23:11:10.947Z",
    "author": "Content Writer Agent",
    "status": "pending"
  },
  {
    "id": "blog-1",
    "title": "Blog Post 1",
    "lastUpdated": "2025-05-07T22:56:49.768Z",
    "author": "Content Writer Agent"
  },
  {
    "id": "blog",
    "title": "Blog",
    "lastUpdated": "2025-05-07T23:07:18.974Z",
    "author": "Content Writer Agent"
  }
]